[
  {
    "Type": "Texture2D",
    "Name": "Icon_Cancel",
    "Properties": {
      "ImportedSize": {
        "X": 64,
        "Y": 64
      },
      "LightingGuid": "7BDDC68E-4BA9B195-6FC67698-3207EF28",
      "CompressionSettings": "TC_Alpha",
      "LODGroup": "TEXTUREGROUP_UI",
      "SRGB": false
    },
    "SizeX": 64,
    "SizeY": 64,
    "PackedData": 1,
    "PixelFormat": "PF_BC4",
    "FirstMipToSerialize": 0,
    "Mips": [
      {
        "BulkData": {
          "BulkDataFlags": "BULKDATA_ForceInlinePayload",
          "ElementCount": 2048,
          "SizeOnDisk": 2048,
          "OffsetInFile": "0x11E0"
        },
        "SizeX": 64,
        "SizeY": 64,
        "SizeZ": 1
      }
    ]
  }
]